flexdb/__init__.py
flexdb/flexdb.py
tests/__init__.py
tests/test_flexdb.py
python_flexdb-0.1.0.dist-info/LICENSE
python_flexdb-0.1.0.dist-info/METADATA
python_flexdb-0.1.0.dist-info/WHEEL
python_flexdb-0.1.0.dist-info/top_level.txt
python_flexdb-0.1.0.dist-info/RECORD
